[
  { "disciple": "CANE", "impostor": "GATTO" },
  { "disciple": "MARE", "impostor": "OCEANO" },
  { "disciple": "PIZZA", "impostor": "FOCACCIA" },
  { "disciple": "ESTATE", "impostor": "PRIMAVERA" },
  { "disciple": "LUNA", "impostor": "SOLE" },
  { "disciple": "CALCIO", "impostor": "BASKET" },
  { "disciple": "TRENO", "impostor": "AUTOBUS" },
  { "disciple": "CAFFÈ", "impostor": "TÈ" },
  { "disciple": "MONTAGNA", "impostor": "COLLINA" },
  { "disciple": "LIBRO", "impostor": "QUADERNO" },
  { "disciple": "CHITARRA", "impostor": "BASSO" },
  { "disciple": "AEREO", "impostor": "ELICOTTERO" },
  { "disciple": "PANINO", "impostor": "TRAMEZZINO" },
  { "disciple": "INVERNO", "impostor": "AUTUNNO" },
  { "disciple": "CINEMA", "impostor": "TEATRO" },
  { "disciple": "PASTA", "impostor": "RISO" },
  { "disciple": "BICICLETTA", "impostor": "MONOPATTINO" },
  { "disciple": "GELATO", "impostor": "SORBETTO" },
  { "disciple": "MEDICO", "impostor": "INFERMIERE" },
  { "disciple": "SCARPE", "impostor": "SANDALI" },
  { "disciple": "VIOLINO", "impostor": "VIOLA" },
  { "disciple": "ROSSO", "impostor": "ARANCIONE" },
  { "disciple": "AUTOMOBILE", "impostor": "MOTO" },
  { "disciple": "TIGRE", "impostor": "LEONE" },
  { "disciple": "ACQUA", "impostor": "BIBITA" },
  { "disciple": "PIANOFORTE", "impostor": "TASTIERA" },
  { "disciple": "BANANA", "impostor": "PERA" },
  { "disciple": "TELEVISIONE", "impostor": "MONITOR" },
  { "disciple": "LETTO", "impostor": "DIVANO" },
  { "disciple": "CAPPELLO", "impostor": "BERRETTO" },
  { "disciple": "FIUME", "impostor": "LAGO" },
  { "disciple": "COMPUTER", "impostor": "TABLET" },
  { "disciple": "CIOCCOLATO", "impostor": "CARAMELLA" },
  { "disciple": "GIORNALE", "impostor": "RIVISTA" },
  { "disciple": "FORCHETTA", "impostor": "CUCCHIAIO" },
  { "disciple": "PORTA", "impostor": "FINESTRA" },
  { "disciple": "TAVOLO", "impostor": "SCRIVANIA" },
  { "disciple": "CAMICIA", "impostor": "MAGLIETTA" },
  { "disciple": "PENNA", "impostor": "MATITA" },
  { "disciple": "OROLOGIO", "impostor": "SVEGLIA" },
  { "disciple": "SEDIA", "impostor": "POLTRONA" },
  { "disciple": "MELA", "impostor": "PESCA" },
  { "disciple": "BOTTIGLIA", "impostor": "BICCHIERE" },
  { "disciple": "NAVE", "impostor": "BARCA" },
  { "disciple": "COLTELLO", "impostor": "FORBICI" },
  { "disciple": "PANTALONI", "impostor": "JEANS" },
  { "disciple": "SMARTPHONE", "impostor": "TELEFONO" },
  { "disciple": "LAMPADA", "impostor": "LAMPADARIO" },
  { "disciple": "ZAINO", "impostor": "BORSA" },
  { "disciple": "BLU", "impostor": "AZZURRO" },
  { "disciple": "COLAZIONE", "impostor": "MERENDA" },
  { "disciple": "PANE", "impostor": "GRISSINO" },
  { "disciple": "MUSEO", "impostor": "GALLERIA" },
  { "disciple": "PARCO", "impostor": "GIARDINO" },
  { "disciple": "BALCONE", "impostor": "TERRAZZA" },
  { "disciple": "SCALA", "impostor": "ASCENSORE" },
  { "disciple": "OMBRELLO", "impostor": "OMBRELLONE" },
  { "disciple": "FRIGORIFERO", "impostor": "CONGELATORE" },
  { "disciple": "FORNO", "impostor": "MICROONDE" },
  { "disciple": "VASCA", "impostor": "DOCCIA" },
  { "disciple": "SPECCHIO", "impostor": "VETRO" },
  { "disciple": "CUSCINO", "impostor": "MATERASSO" },
  { "disciple": "CANDELA", "impostor": "TORCIA" },
  { "disciple": "QUADRO", "impostor": "POSTER" },
  { "disciple": "TAPPETO", "impostor": "MOQUETTE" },
  { "disciple": "DOCENTE", "impostor": "PROFESSORE" },
  { "disciple": "STUDENTE", "impostor": "ALUNNO" },
  { "disciple": "UNIVERSITÀ", "impostor": "SCUOLA" },
  { "disciple": "ESAME", "impostor": "TEST" },
  { "disciple": "VOTO", "impostor": "GIUDIZIO" },
  { "disciple": "AULA", "impostor": "CLASSE" },
  { "disciple": "LAVAGNA", "impostor": "PANNELLO" },
  { "disciple": "ZAINO", "impostor": "CARTELLA" },
  { "disciple": "CALENDARIO", "impostor": "AGENDA" },
  { "disciple": "CALCOLATRICE", "impostor": "COMPUTER" },
  { "disciple": "DIZIONARIO", "impostor": "ENCICLOPEDIA" },
  { "disciple": "ROMANZO", "impostor": "RACCONTO" },
  { "disciple": "POESIA", "impostor": "LIRICA" },
  { "disciple": "GIOCO", "impostor": "SPORT" },
  { "disciple": "SQUADRA", "impostor": "GRUPPO" },
  { "disciple": "VITTORIA", "impostor": "TRIONFO" },
  { "disciple": "SCONFITTA", "impostor": "PERDITA" },
  { "disciple": "STADIO", "impostor": "PALESTRA" },
  { "disciple": "PISCINA", "impostor": "VASCA" },
  { "disciple": "CORRERE", "impostor": "CAMMINARE" },
  { "disciple": "SALTARE", "impostor": "BALLARE" },
  { "disciple": "NUOTARE", "impostor": "GALLEGGIARE" },
  { "disciple": "VOLARE", "impostor": "PLANARE" },
  { "disciple": "GUIDARE", "impostor": "PILOTARE" },
  { "disciple": "CUCINARE", "impostor": "PREPARARE" },
  { "disciple": "MANGIARE", "impostor": "GUSTARE" },
  { "disciple": "BERE", "impostor": "SORSEGGIARE" },
  { "disciple": "DORMIRE", "impostor": "RIPOSARE" },
  { "disciple": "SVEGLIARSI", "impostor": "ALZARSI" },
  { "disciple": "RIDERE", "impostor": "SORRIDERE" },
  { "disciple": "PIANGERE", "impostor": "SINGHIOZZARE" },
  { "disciple": "PARLARE", "impostor": "CHIACCHIERARE" },
  { "disciple": "ASCOLTARE", "impostor": "SENTIRE" },
  { "disciple": "GUARDARE", "impostor": "OSSERVARE" },
  { "disciple": "CALDO", "impostor": "TIEPIDO" },
  { "disciple": "FREDDO", "impostor": "FRESCO" },
  { "disciple": "GRANDE", "impostor": "ENORME" },
  { "disciple": "PICCOLO", "impostor": "MINUSCOLO" },
  { "disciple": "VELOCE", "impostor": "RAPIDO" },
  { "disciple": "LENTO", "impostor": "PIGRO" },
  { "disciple": "FORTE", "impostor": "POTENTE" },
  { "disciple": "DEBOLE", "impostor": "FRAGILE" },
  { "disciple": "RICCO", "impostor": "BENESTANTE" },
  { "disciple": "POVERO", "impostor": "INDIGENTE" },
  { "disciple": "FELICE", "impostor": "CONTENTO" },
  { "disciple": "TRISTE", "impostor": "MELANCONICO" },
  { "disciple": "ARRABBIATO", "impostor": "FURIOSO" },
  { "disciple": "CALMO", "impostor": "SERENO" },
  { "disciple": "STANCO", "impostor": "ESAUSTO" },
  { "disciple": "ENERGICO", "impostor": "VIVACE" },
  { "disciple": "GIOVANE", "impostor": "ADOLESCENTE" },
  { "disciple": "VECCHIO", "impostor": "ANZIANO" },
  { "disciple": "NUOVO", "impostor": "RECENTE" },
  { "disciple": "ANTICO", "impostor": "STORICO" },
  { "disciple": "PULITO", "impostor": "IMMACOLATO" },
  { "disciple": "SPORCO", "impostor": "SUDICIO" },
  { "disciple": "BELLO", "impostor": "ATTRAENTE" },
  { "disciple": "BRUTTO", "impostor": "SGRADEVOLE" },
  { "disciple": "DOLCE", "impostor": "ZUCCHERATO" },
  { "disciple": "SALATO", "impostor": "SAPIDO" },
  { "disciple": "AMARO", "impostor": "ASPRO" },
  { "disciple": "ACIDO", "impostor": "AGRUMATO" },
  { "disciple": "MORBIDO", "impostor": "SOFFICE" },
  { "disciple": "DURO", "impostor": "RIGIDO" },
  { "disciple": "LISCIO", "impostor": "LEVIGATO" },
  { "disciple": "RUVIDO", "impostor": "SCABRO" },
  { "disciple": "ALTO", "impostor": "ELEVATO" },
  { "disciple": "BASSO", "impostor": "CORTO" },
  { "disciple": "LARGO", "impostor": "AMPIO" },
  { "disciple": "STRETTO", "impostor": "ANGUSTO" },
  { "disciple": "LUNGO", "impostor": "ESTESO" },
  { "disciple": "CORTO", "impostor": "BREVE" },
  { "disciple": "PESANTE", "impostor": "MASSICCIO" },
  { "disciple": "LEGGERO", "impostor": "SOTTILE" },
  { "disciple": "SPESSO", "impostor": "DENSO" },
  { "disciple": "SOTTILE", "impostor": "ESILE" },
  { "disciple": "PIENO", "impostor": "COLMO" },
  { "disciple": "VUOTO", "impostor": "DESERTO" },
  { "disciple": "APERTO", "impostor": "SPALANCATO" },
  { "disciple": "CHIUSO", "impostor": "SIGILLATO" },
  { "disciple": "VICINO", "impostor": "PROSSIMO" },
  { "disciple": "LONTANO", "impostor": "DISTANTE" },
  { "disciple": "DENTRO", "impostor": "INTERNO" },
  { "disciple": "FUORI", "impostor": "ESTERNO" },
  { "disciple": "SOPRA", "impostor": "OLTRE" },
  { "disciple": "SOTTO", "impostor": "INFERIORE" },
  { "disciple": "DAVANTI", "impostor": "ANTERIORE" },
  { "disciple": "DIETRO", "impostor": "POSTERIORE" },
  { "disciple": "DESTRA", "impostor": "DRITTA" },
  { "disciple": "SINISTRA", "impostor": "MANCINA" },
  { "disciple": "CENTRO", "impostor": "MEZZO" },
  { "disciple": "ANGOLO", "impostor": "VERTICE" },
  { "disciple": "CERCHIO", "impostor": "CIRCONFERENZA" },
  { "disciple": "QUADRATO", "impostor": "RETTANGOLO" },
  { "disciple": "TRIANGOLO", "impostor": "PIRAMIDE" },
  { "disciple": "STELLA", "impostor": "ASTRO" },
  { "disciple": "PIANETA", "impostor": "SATELLITE" },
  { "disciple": "GALASSIA", "impostor": "UNIVERSO" },
  { "disciple": "SOLE", "impostor": "STELLA" },
  { "disciple": "TERRA", "impostor": "MONDO" },
  { "disciple": "CIELO", "impostor": "ATMOSFERA" },
  { "disciple": "NUVOLA", "impostor": "NEBBIA" },
  { "disciple": "PIOGGIA", "impostor": "TEMPORALE" },
  { "disciple": "NEVE", "impostor": "GRANDINE" },
  { "disciple": "VENTO", "impostor": "BREZZA" },
  { "disciple": "TEMPESTA", "impostor": "URAGANO" },
  { "disciple": "FULMINE", "impostor": "SAETTA" },
  { "disciple": "TUONO", "impostor": "BOATO" },
  { "disciple": "ARCOBALENO", "impostor": "IRIDE" },
  { "disciple": "ALBA", "impostor": "AURORA" },
  { "disciple": "TRAMONTO", "impostor": "CREPUSCOLO" },
  { "disciple": "GIORNO", "impostor": "GIORNATA" },
  { "disciple": "NOTTE", "impostor": "NOTTATA" },
  { "disciple": "MATTINA", "impostor": "MATTINO" },
  { "disciple": "POMERIGGIO", "impostor": "SERA" },
  { "disciple": "SETTIMANA", "impostor": "PERIODO" },
  { "disciple": "MESE", "impostor": "MENSILE" },
  { "disciple": "ANNO", "impostor": "ANNATA" },
  { "disciple": "SECOLO", "impostor": "ERA" },
  { "disciple": "ORA", "impostor": "TEMPO" },
  { "disciple": "MINUTO", "impostor": "MOMENTO" },
  { "disciple": "SECONDO", "impostor": "ATTIMO" },
  { "disciple": "PASSATO", "impostor": "TRASCORSO" },
  { "disciple": "PRESENTE", "impostor": "ATTUALE" },
  { "disciple": "FUTURO", "impostor": "AVVENIRE" },
  { "disciple": "IERI", "impostor": "DIANZI" },
  { "disciple": "OGGI", "impostor": "ADESSO" },
  { "disciple": "DOMANI", "impostor": "INDOMANI" },
  { "disciple": "PRIMAVERA", "impostor": "ESTATE" },
  { "disciple": "AUTUNNO", "impostor": "INVERNO" },
  { "disciple": "GENNAIO", "impostor": "FEBBRAIO" },
  { "disciple": "MARZO", "impostor": "APRILE" },
  { "disciple": "MAGGIO", "impostor": "GIUGNO" },
  { "disciple": "LUGLIO", "impostor": "AGOSTO" },
  { "disciple": "SETTEMBRE", "impostor": "OTTOBRE" }
]

